poemai_utils/__init__.py
poemai_utils/ai_model.py
poemai_utils/basic_types_utils.py
poemai_utils/collect_text_files.py
poemai_utils/configuration_api.py
poemai_utils/dict_index.py
poemai_utils/dir_hash.py
poemai_utils/enum_utils.py
poemai_utils/excel_writer.py
poemai_utils/expiring_cache.py
poemai_utils/file_utils.py
poemai_utils/operations_utils.py
poemai_utils/progress_logger.py
poemai_utils/reranker.py
poemai_utils/simple.py
poemai_utils/simple_cache.py
poemai_utils/state_machine.py
poemai_utils/time_utils.py
poemai_utils/utils_config.py
poemai_utils/web_utils.py
poemai_utils/yaml_utils.py
poemai_utils/aws/__init__.py
poemai_utils/aws/boto3_proxy.py
poemai_utils/aws/dao_helper.py
poemai_utils/aws/dynamodb.py
poemai_utils/aws/dynamodb_emulator.py
poemai_utils/aws/lambda_api_light.py
poemai_utils/aws/lambda_utils.py
poemai_utils/aws/local_lambda_runtime.py
poemai_utils/bedrock/ask_bedrock.py
poemai_utils/embeddings/__init__.py
poemai_utils/embeddings/cross_similarity_analyzer.py
poemai_utils/embeddings/embedder_base.py
poemai_utils/embeddings/embedder_factory.py
poemai_utils/embeddings/embedding_cache.py
poemai_utils/embeddings/embedding_store.py
poemai_utils/embeddings/openai_embedder.py
poemai_utils/embeddings/openai_embedder_lean.py
poemai_utils/embeddings/self_similarity_analyzer.py
poemai_utils/embeddings/sentence_transformer_embedder.py
poemai_utils/embeddings/sentence_transformer_embedding_model.py
poemai_utils/embeddings/sgpt_embedder.py
poemai_utils/embeddings/simple.py
poemai_utils/llama_cpp/__init__.py
poemai_utils/llama_cpp/ask_llama.py
poemai_utils/monitoring/health_checks.py
poemai_utils/openai/__init__.py
poemai_utils/openai/ask.py
poemai_utils/openai/ask_lean.py
poemai_utils/openai/ask_responses.py
poemai_utils/openai/llm_answer_cache.py
poemai_utils/openai/llm_answer_cache_dao.py
poemai_utils/openai/openai_model.py
poemai_utils/tools/html_to_md_ai.py
poemai_utils-3.1.2.dist-info/licenses/LICENSE.txt
poemai_utils-3.1.2.dist-info/METADATA
poemai_utils-3.1.2.dist-info/WHEEL
poemai_utils-3.1.2.dist-info/top_level.txt
poemai_utils-3.1.2.dist-info/RECORD
