Metadata-Version: 2.4
Name: poemai-utils
Version: 3.1.2
Summary: Add a short description here!
Home-page: https://github.com/poemAI-ch/poemai-utils
Author: Markus Emmenegger
Author-email: markus.emmenegger@poemai.ch
License: MIT
Project-URL: Documentation, https://github.com/poemAI-ch/poemai-utils
Project-URL: Source, https://github.com/poemAI-ch/poemai-utils
Platform: any
Classifier: Development Status :: 4 - Beta
Classifier: Programming Language :: Python
License-File: LICENSE.txt
Requires-Dist: importlib-metadata; python_version < "3.8"
Requires-Dist: sqlitedict
Requires-Dist: httpx
Requires-Dist: numpy
Requires-Dist: openai
Requires-Dist: python-box~=7.0
Provides-Extra: testing
Requires-Dist: setuptools; extra == "testing"
Requires-Dist: pytest; extra == "testing"
Requires-Dist: pytest-cov; extra == "testing"
Requires-Dist: transformers; extra == "testing"
Dynamic: license-file
